badboy/__init__.py
badboy/__main__.py
badboy-0.1.0.dist-info/LICENSE
badboy-0.1.0.dist-info/METADATA
badboy-0.1.0.dist-info/WHEEL
badboy-0.1.0.dist-info/entry_points.txt
badboy-0.1.0.dist-info/top_level.txt
badboy-0.1.0.dist-info/RECORD
