Metadata-Version: 2.1
Name: badboy
Version: 0.1.0
Summary: A library with computational and mathematical functions!
Home-page: https://github.com/AitzazImtiaz/Bad-Boy
Author: AitzazImtiaz
License: MIT
Classifier: Intended Audience :: Developers
Classifier: License :: OSI Approved :: MIT License
Classifier: Programming Language :: Python
Classifier: Programming Language :: Python :: 3
Classifier: Programming Language :: Python :: 3.6
Classifier: Programming Language :: Python :: 3.7
Classifier: Programming Language :: Python :: 3.8
Classifier: Programming Language :: Python :: 3.9
Classifier: Operating System :: OS Independent
License-File: LICENSE
